{"data":{"Year":[2014,2016,2019,2014,2016,2019,2014,2016,2019,2014,2016,2019,2014,2016,2019,2014,2016,2019],"SDG Series":["Average income of large-scale food producers [2.3.2]","Average income of large-scale food producers [2.3.2]","Average income of large-scale food producers [2.3.2]","Average income of large-scale food producers [2.3.2]","Average income of large-scale food producers [2.3.2]","Average income of large-scale food producers [2.3.2]","Average income of large-scale food producers [2.3.2]","Average income of large-scale food producers [2.3.2]","Average income of large-scale food producers [2.3.2]","Average income of small-scale food producers [2.3.2]","Average income of small-scale food producers [2.3.2]","Average income of small-scale food producers [2.3.2]","Average income of small-scale food producers [2.3.2]","Average income of small-scale food producers [2.3.2]","Average income of small-scale food producers [2.3.2]","Average income of small-scale food producers [2.3.2]","Average income of small-scale food producers [2.3.2]","Average income of small-scale food producers [2.3.2]"],"Sex":[null,null,null,"Female","Female","Female","Male","Male","Male",null,null,null,"Female","Female","Female","Male","Male","Male"],"Value":[846.39038,979.01422,1384.3358,815.6485,1181.6605,1143.6064,851.67847,947.16846,1414.6019,396.58,436.67,509.83,300.97,298.45,377.45,427.97,488.62,562.72]},"edges":{"From":["SDG Series"],"To":["Sex"]}}